fibonacci_api/__about__.py
fibonacci_api/__init__.py
fibonacci_api/_block.py
fibonacci_api/crud.py
fibonacci_api/main.py
fibonacci_api/types.py
fibonacci_api-0.0.1.dist-info/METADATA
fibonacci_api-0.0.1.dist-info/WHEEL
fibonacci_api-0.0.1.dist-info/licenses/LICENSE.txt
fibonacci_api-0.0.1.dist-info/RECORD
