Metadata-Version: 2.4
Name: fibonacci-api
Version: 0.0.1
Project-URL: Documentation, https://github.com/Timon Viola/fibonacci-api#readme
Project-URL: Issues, https://github.com/Timon Viola/fibonacci-api/issues
Project-URL: Source, https://github.com/Timon Viola/fibonacci-api
Author-email: Timon Viola <viotimo@dfds.com>
License-Expression: MIT
License-File: LICENSE.txt
Classifier: Development Status :: 4 - Beta
Classifier: Programming Language :: Python
Classifier: Programming Language :: Python :: 3.8
Classifier: Programming Language :: Python :: 3.9
Classifier: Programming Language :: Python :: 3.10
Classifier: Programming Language :: Python :: 3.11
Classifier: Programming Language :: Python :: 3.12
Classifier: Programming Language :: Python :: Implementation :: CPython
Classifier: Programming Language :: Python :: Implementation :: PyPy
Requires-Python: >=3.8
Requires-Dist: fastapi[all]<0.116.0,>=0.115.12
